setup.py
XTLLib/SetVars.py
XTLLib/__init__.py
XTLLib/achooser.py
XTLLib/fwrite.py
XTLLib/linuxdl.py
XTLLib/muulter.py
XTLLib/runaspowershell.py
XTLLib/runqol.py
XTLLib.egg-info/PKG-INFO
XTLLib.egg-info/SOURCES.txt
XTLLib.egg-info/dependency_links.txt
XTLLib.egg-info/requires.txt
XTLLib.egg-info/top_level.txt