Metadata-Version: 2.1
Name: XTLLib
Version: 0.6
Summary: Xemulated's Library for XToolBox
Home-page: https://github.com/xemulat
Download-URL: https://github.com/xemulat/XTLLib/archive/refs/tags/0.6.tar.gz
Author: Xemulated
Author-email: xemulated@tuta.io
License: mit
Keywords: QOL,xemulated,downloader
Classifier: Development Status :: 3 - Alpha
Classifier: Intended Audience :: Developers
Classifier: Topic :: Software Development :: Build Tools
Classifier: License :: OSI Approved :: MIT License
Classifier: Programming Language :: Python :: 3.11
Classifier: Programming Language :: Python :: 3.10
